frequenz/api/common/v1/__init__.py
frequenz/api/common/v1/grid/__init__.py
frequenz/api/common/v1/market/__init__.py
frequenz/api/common/v1/pagination/__init__.py
frequenz/api/electricity_trading/__init__.py
frequenz/api/electricity_trading/conftest.py
frequenz/api/electricity_trading/py.typed
frequenz/api/electricity_trading/v1/__init__.py
frequenz/api/electricity_trading/v1/electricity_trading_pb2.py
frequenz/api/electricity_trading/v1/electricity_trading_pb2.pyi
frequenz/api/electricity_trading/v1/electricity_trading_pb2_grpc.py
frequenz/api/electricity_trading/v1/electricity_trading_pb2_grpc.pyi
frequenz/api/electricity_trading/v1/py.typed
frequenz_api_electricity_trading-0.8.1.dist-info/licenses/LICENSE
frequenz_api_electricity_trading-0.8.1.dist-info/METADATA
frequenz_api_electricity_trading-0.8.1.dist-info/WHEEL
frequenz_api_electricity_trading-0.8.1.dist-info/top_level.txt
frequenz_api_electricity_trading-0.8.1.dist-info/RECORD
